pygbrowse/__init__.py
pygbrowse/datasources.py
pygbrowse/intervaloverlaps.py
pygbrowse/plots.py
pygbrowse/romannumerals.py
pygbrowse/utilities.py
pygbrowse-0.3.3.dist-info/METADATA
pygbrowse-0.3.3.dist-info/RECORD
pygbrowse-0.3.3.dist-info/WHEEL
pygbrowse-0.3.3.dist-info/top_level.txt
