Metadata-Version: 2.1
Name: pygbrowse
Version: 0.3.3
Summary: Tools for making plots of genomic datasets in a genome-browser-like format 
Home-page: https://github.com/phageghost/python-genome-browser
Author: phageghost
Author-email: pygbrowse@phageghost.net
License: MIT
Platform: UNKNOWN
Classifier: Programming Language :: Python :: 3
Classifier: License :: OSI Approved :: MIT License
Classifier: Operating System :: OS Independent
Requires-Dist: numpy
Requires-Dist: scipy
Requires-Dist: pandas
Requires-Dist: matplotlib
Requires-Dist: seaborn
Requires-Dist: pysam
Requires-Dist: intervaltree
